[
    {
        "comment": "/**\n */",
        "meta": {
            "range": [
                8,
                1708
            ],
            "filename": "progress.js",
            "lineno": 3,
            "columnno": 0,
            "path": "C:\\Users\\ndiin\\Documents\\ndiing3\\material\\src\\material\\progress",
            "code": {
                "id": "astnode100000002",
                "name": "Progress",
                "type": "ClassDeclaration",
                "paramnames": []
            }
        },
        "name": "Progress",
        "longname": "Progress",
        "kind": "class",
        "scope": "global",
        "undocumented": true
    },
    {
        "comment": "/**\n     */",
        "meta": {
            "range": [
                45,
                194
            ],
            "filename": "progress.js",
            "lineno": 6,
            "columnno": 4,
            "path": "C:\\Users\\ndiin\\Documents\\ndiing3\\material\\src\\material\\progress",
            "code": {
                "id": "astnode100000005",
                "name": "Progress",
                "type": "MethodDefinition",
                "paramnames": []
            },
            "vars": {
                "": null
            }
        },
        "name": "Progress",
        "longname": "Progress",
        "kind": "class",
        "scope": "global",
        "params": [],
        "undocumented": true
    },
    {
        "comment": "/**\n */",
        "meta": {
            "range": [
                8,
                1708
            ],
            "filename": "progress.js",
            "lineno": 3,
            "columnno": 0,
            "path": "C:\\Users\\ndiin\\Documents\\ndiing3\\material\\src\\material\\progress",
            "code": {
                "id": "astnode100000002",
                "name": "Progress",
                "type": "ClassDeclaration",
                "paramnames": []
            }
        },
        "name": "Progress",
        "longname": "Progress",
        "kind": "class",
        "scope": "global"
    },
    {
        "comment": "",
        "meta": {
            "range": [
                69,
                90
            ],
            "filename": "progress.js",
            "lineno": 7,
            "columnno": 8,
            "path": "C:\\Users\\ndiin\\Documents\\ndiing3\\material\\src\\material\\progress",
            "code": {
                "id": "astnode100000010",
                "name": "this.startTime",
                "type": "Literal",
                "value": null,
                "paramnames": []
            }
        },
        "undocumented": true,
        "name": "startTime",
        "longname": "Progress#startTime",
        "kind": "member",
        "memberof": "Progress",
        "scope": "instance"
    },
    {
        "comment": "",
        "meta": {
            "range": [
                100,
                117
            ],
            "filename": "progress.js",
            "lineno": 8,
            "columnno": 8,
            "path": "C:\\Users\\ndiin\\Documents\\ndiing3\\material\\src\\material\\progress",
            "code": {
                "id": "astnode100000016",
                "name": "this.duration",
                "type": "Literal",
                "value": 0,
                "paramnames": []
            }
        },
        "undocumented": true,
        "name": "duration",
        "longname": "Progress#duration",
        "kind": "member",
        "memberof": "Progress",
        "scope": "instance"
    },
    {
        "comment": "",
        "meta": {
            "range": [
                127,
                148
            ],
            "filename": "progress.js",
            "lineno": 9,
            "columnno": 8,
            "path": "C:\\Users\\ndiin\\Documents\\ndiing3\\material\\src\\material\\progress",
            "code": {
                "id": "astnode100000022",
                "name": "this.requestId",
                "type": "Literal",
                "value": null,
                "paramnames": []
            }
        },
        "undocumented": true,
        "name": "requestId",
        "longname": "Progress#requestId",
        "kind": "member",
        "memberof": "Progress",
        "scope": "instance"
    },
    {
        "comment": "",
        "meta": {
            "range": [
                158,
                187
            ],
            "filename": "progress.js",
            "lineno": 10,
            "columnno": 8,
            "path": "C:\\Users\\ndiin\\Documents\\ndiing3\\material\\src\\material\\progress",
            "code": {
                "id": "astnode100000028",
                "name": "this.progressIndicator",
                "type": "Literal",
                "value": null,
                "paramnames": []
            }
        },
        "undocumented": true,
        "name": "progressIndicator",
        "longname": "Progress#progressIndicator",
        "kind": "member",
        "memberof": "Progress",
        "scope": "instance"
    },
    {
        "comment": "/**\n     */",
        "meta": {
            "range": [
                216,
                530
            ],
            "filename": "progress.js",
            "lineno": 15,
            "columnno": 4,
            "path": "C:\\Users\\ndiin\\Documents\\ndiing3\\material\\src\\material\\progress",
            "code": {
                "id": "astnode100000033",
                "name": "Progress#render",
                "type": "MethodDefinition",
                "paramnames": []
            },
            "vars": {
                "": null
            }
        },
        "name": "render",
        "longname": "Progress#render",
        "kind": "function",
        "memberof": "Progress",
        "scope": "instance",
        "params": []
    },
    {
        "comment": "",
        "meta": {
            "range": [
                278,
                350
            ],
            "filename": "progress.js",
            "lineno": 17,
            "columnno": 12,
            "path": "C:\\Users\\ndiin\\Documents\\ndiing3\\material\\src\\material\\progress",
            "code": {
                "id": "astnode100000044",
                "name": "this.progressIndicator",
                "type": "CallExpression",
                "value": "",
                "paramnames": []
            }
        },
        "undocumented": true,
        "name": "progressIndicator",
        "longname": "Progress#progressIndicator",
        "kind": "member",
        "memberof": "Progress",
        "scope": "instance"
    },
    {
        "comment": "/**\n     * @param {Any} [newDuration]\n     */",
        "meta": {
            "range": [
                586,
                889
            ],
            "filename": "progress.js",
            "lineno": 26,
            "columnno": 4,
            "path": "C:\\Users\\ndiin\\Documents\\ndiing3\\material\\src\\material\\progress",
            "code": {
                "id": "astnode100000078",
                "name": "Progress#start",
                "type": "MethodDefinition",
                "paramnames": [
                    "newDuration"
                ]
            },
            "vars": {
                "": null
            }
        },
        "params": [
            {
                "type": {
                    "names": [
                        "Any"
                    ]
                },
                "optional": true,
                "name": "newDuration"
            }
        ],
        "name": "start",
        "longname": "Progress#start",
        "kind": "function",
        "memberof": "Progress",
        "scope": "instance"
    },
    {
        "comment": "",
        "meta": {
            "range": [
                615,
                643
            ],
            "filename": "progress.js",
            "lineno": 27,
            "columnno": 8,
            "path": "C:\\Users\\ndiin\\Documents\\ndiing3\\material\\src\\material\\progress",
            "code": {
                "id": "astnode100000084",
                "name": "this.duration",
                "type": "Identifier",
                "value": "newDuration",
                "paramnames": []
            }
        },
        "undocumented": true,
        "name": "duration",
        "longname": "Progress#duration",
        "kind": "member",
        "memberof": "Progress",
        "scope": "instance"
    },
    {
        "comment": "",
        "meta": {
            "range": [
                696,
                730
            ],
            "filename": "progress.js",
            "lineno": 29,
            "columnno": 12,
            "path": "C:\\Users\\ndiin\\Documents\\ndiing3\\material\\src\\material\\progress",
            "code": {
                "id": "astnode100000097",
                "name": "this.startTime",
                "type": "CallExpression",
                "value": "",
                "paramnames": []
            }
        },
        "undocumented": true,
        "name": "startTime",
        "longname": "Progress#startTime",
        "kind": "member",
        "memberof": "Progress",
        "scope": "instance"
    },
    {
        "comment": "",
        "meta": {
            "range": [
                812,
                872
            ],
            "filename": "progress.js",
            "lineno": 33,
            "columnno": 12,
            "path": "C:\\Users\\ndiin\\Documents\\ndiing3\\material\\src\\material\\progress",
            "code": {
                "id": "astnode100000117",
                "name": "this.requestId",
                "type": "CallExpression",
                "value": "",
                "paramnames": []
            }
        },
        "undocumented": true,
        "name": "requestId",
        "longname": "Progress#requestId",
        "kind": "member",
        "memberof": "Progress",
        "scope": "instance"
    },
    {
        "comment": "/**\n     * @param {Any} [currentTime]\n     */",
        "meta": {
            "range": [
                945,
                1383
            ],
            "filename": "progress.js",
            "lineno": 40,
            "columnno": 4,
            "path": "C:\\Users\\ndiin\\Documents\\ndiing3\\material\\src\\material\\progress",
            "code": {
                "id": "astnode100000130",
                "name": "Progress#step",
                "type": "MethodDefinition",
                "paramnames": [
                    "currentTime"
                ]
            },
            "vars": {
                "": null
            }
        },
        "params": [
            {
                "type": {
                    "names": [
                        "Any"
                    ]
                },
                "optional": true,
                "name": "currentTime"
            }
        ],
        "name": "step",
        "longname": "Progress#step",
        "kind": "function",
        "memberof": "Progress",
        "scope": "instance"
    },
    {
        "comment": "",
        "meta": {
            "range": [
                1022,
                1060
            ],
            "filename": "progress.js",
            "lineno": 42,
            "columnno": 12,
            "path": "C:\\Users\\ndiin\\Documents\\ndiing3\\material\\src\\material\\progress",
            "code": {
                "id": "astnode100000142",
                "name": "elapsed",
                "type": "BinaryExpression",
                "value": ""
            }
        },
        "undocumented": true,
        "name": "elapsed",
        "longname": "<anonymous>~elapsed",
        "kind": "member",
        "memberof": "<anonymous>",
        "scope": "inner",
        "params": []
    },
    {
        "comment": "",
        "meta": {
            "range": [
                1074,
                1121
            ],
            "filename": "progress.js",
            "lineno": 43,
            "columnno": 12,
            "path": "C:\\Users\\ndiin\\Documents\\ndiing3\\material\\src\\material\\progress",
            "code": {
                "id": "astnode100000150",
                "name": "progress",
                "type": "CallExpression",
                "value": ""
            }
        },
        "undocumented": true,
        "name": "progress",
        "longname": "<anonymous>~progress",
        "kind": "member",
        "memberof": "<anonymous>",
        "scope": "inner",
        "params": []
    },
    {
        "comment": "",
        "meta": {
            "range": [
                1131,
                1173
            ],
            "filename": "progress.js",
            "lineno": 44,
            "columnno": 8,
            "path": "C:\\Users\\ndiin\\Documents\\ndiing3\\material\\src\\material\\progress",
            "code": {
                "id": "astnode100000163",
                "name": "this.progressIndicator.max",
                "type": "MemberExpression",
                "value": "this.duration",
                "paramnames": []
            }
        },
        "undocumented": true,
        "name": "max",
        "longname": "Progress#progressIndicator.max",
        "kind": "member",
        "memberof": "Progress#progressIndicator",
        "scope": "static"
    },
    {
        "comment": "",
        "meta": {
            "range": [
                1183,
                1221
            ],
            "filename": "progress.js",
            "lineno": 45,
            "columnno": 8,
            "path": "C:\\Users\\ndiin\\Documents\\ndiing3\\material\\src\\material\\progress",
            "code": {
                "id": "astnode100000173",
                "name": "this.progressIndicator.value",
                "type": "Identifier",
                "value": "elapsed",
                "paramnames": []
            }
        },
        "undocumented": true,
        "name": "value",
        "longname": "Progress#progressIndicator.value",
        "kind": "member",
        "memberof": "Progress#progressIndicator",
        "scope": "static"
    },
    {
        "comment": "",
        "meta": {
            "range": [
                1263,
                1323
            ],
            "filename": "progress.js",
            "lineno": 47,
            "columnno": 12,
            "path": "C:\\Users\\ndiin\\Documents\\ndiing3\\material\\src\\material\\progress",
            "code": {
                "id": "astnode100000186",
                "name": "this.requestId",
                "type": "CallExpression",
                "value": "",
                "paramnames": []
            }
        },
        "undocumented": true,
        "name": "requestId",
        "longname": "Progress#requestId",
        "kind": "member",
        "memberof": "Progress",
        "scope": "instance"
    },
    {
        "comment": "/**\n     */",
        "meta": {
            "range": [
                1405,
                1557
            ],
            "filename": "progress.js",
            "lineno": 55,
            "columnno": 4,
            "path": "C:\\Users\\ndiin\\Documents\\ndiing3\\material\\src\\material\\progress",
            "code": {
                "id": "astnode100000205",
                "name": "Progress#remove",
                "type": "MethodDefinition",
                "paramnames": []
            },
            "vars": {
                "": null
            }
        },
        "name": "remove",
        "longname": "Progress#remove",
        "kind": "function",
        "memberof": "Progress",
        "scope": "instance",
        "params": []
    },
    {
        "comment": "",
        "meta": {
            "range": [
                1511,
                1540
            ],
            "filename": "progress.js",
            "lineno": 58,
            "columnno": 12,
            "path": "C:\\Users\\ndiin\\Documents\\ndiing3\\material\\src\\material\\progress",
            "code": {
                "id": "astnode100000222",
                "name": "this.progressIndicator",
                "type": "Literal",
                "value": null,
                "paramnames": []
            }
        },
        "undocumented": true,
        "name": "progressIndicator",
        "longname": "Progress#progressIndicator",
        "kind": "member",
        "memberof": "Progress",
        "scope": "instance"
    },
    {
        "comment": "/**\n     */",
        "meta": {
            "range": [
                1579,
                1706
            ],
            "filename": "progress.js",
            "lineno": 64,
            "columnno": 4,
            "path": "C:\\Users\\ndiin\\Documents\\ndiing3\\material\\src\\material\\progress",
            "code": {
                "id": "astnode100000227",
                "name": "Progress#reset",
                "type": "MethodDefinition",
                "paramnames": []
            },
            "vars": {
                "": null
            }
        },
        "name": "reset",
        "longname": "Progress#reset",
        "kind": "function",
        "memberof": "Progress",
        "scope": "instance",
        "params": []
    },
    {
        "comment": "",
        "meta": {
            "range": [
                1597,
                1618
            ],
            "filename": "progress.js",
            "lineno": 65,
            "columnno": 8,
            "path": "C:\\Users\\ndiin\\Documents\\ndiing3\\material\\src\\material\\progress",
            "code": {
                "id": "astnode100000232",
                "name": "this.startTime",
                "type": "Literal",
                "value": null,
                "paramnames": []
            }
        },
        "undocumented": true,
        "name": "startTime",
        "longname": "Progress#startTime",
        "kind": "member",
        "memberof": "Progress",
        "scope": "instance"
    },
    {
        "comment": "",
        "meta": {
            "range": [
                1628,
                1645
            ],
            "filename": "progress.js",
            "lineno": 66,
            "columnno": 8,
            "path": "C:\\Users\\ndiin\\Documents\\ndiing3\\material\\src\\material\\progress",
            "code": {
                "id": "astnode100000238",
                "name": "this.duration",
                "type": "Literal",
                "value": 0,
                "paramnames": []
            }
        },
        "undocumented": true,
        "name": "duration",
        "longname": "Progress#duration",
        "kind": "member",
        "memberof": "Progress",
        "scope": "instance"
    },
    {
        "comment": "",
        "meta": {
            "range": [
                1655,
                1676
            ],
            "filename": "progress.js",
            "lineno": 67,
            "columnno": 8,
            "path": "C:\\Users\\ndiin\\Documents\\ndiing3\\material\\src\\material\\progress",
            "code": {
                "id": "astnode100000244",
                "name": "this.requestId",
                "type": "Literal",
                "value": null,
                "paramnames": []
            }
        },
        "undocumented": true,
        "name": "requestId",
        "longname": "Progress#requestId",
        "kind": "member",
        "memberof": "Progress",
        "scope": "instance"
    },
    {
        "comment": "",
        "meta": {
            "range": [
                1718,
                1726
            ],
            "filename": "progress.js",
            "lineno": 71,
            "columnno": 9,
            "path": "C:\\Users\\ndiin\\Documents\\ndiing3\\material\\src\\material\\progress",
            "code": {
                "id": "astnode100000255",
                "name": "exports.Progress",
                "type": "Identifier"
            }
        },
        "undocumented": true,
        "name": "Progress",
        "longname": "Progress",
        "kind": "member",
        "scope": "global"
    },
    {
        "kind": "package",
        "longname": "package:undefined",
        "files": [
            "C:\\Users\\ndiin\\Documents\\ndiing3\\material\\src\\material\\progress\\progress.js"
        ]
    }
]
